Metadata-Version: 2.4
Name: createfa
Version: 1.0.3
Summary: Un générateur d'applications FastAPI avec structure complète
Home-page: https://github.com/bonitoFotso/create_fastapi
Author: Bonito Fotso
Author-email: Bonito Fotso <bonitofotso55@gmail.com>
License: MIT
Project-URL: Homepage, https://github.com/bonitoFotso/create_fastapi
Project-URL: Bug Tracker, https://github.com/bonitoFotso/create_fastapi/issues
Keywords: fastapi,create,api,web,framework
Classifier: Development Status :: 4 - Beta
Classifier: Intended Audience :: Developers
Classifier: License :: OSI Approved :: MIT License
Classifier: Operating System :: OS Independent
Classifier: Programming Language :: Python :: 3
Classifier: Programming Language :: Python :: 3.8
Classifier: Programming Language :: Python :: 3.9
Classifier: Programming Language :: Python :: 3.10
Classifier: Programming Language :: Python :: 3.11
Classifier: Programming Language :: Python :: 3.12
Classifier: Topic :: Software Development :: Code Generators
Requires-Python: >=3.8
License-File: LICENSE
Requires-Dist: click>=8.0.0
Requires-Dist: jinja2>=3.0.0
Requires-Dist: colorama>=0.4.0
Dynamic: author
Dynamic: home-page
Dynamic: license-file
Dynamic: requires-python
